moneybox/__init__.py
moneybox/api_client.py
moneybox/api_response.py
moneybox/configuration.py
moneybox/exceptions.py
moneybox/rest.py
moneybox/api/__init__.py
moneybox/api/auth_api.py
moneybox/api/currency_api.py
moneybox/api/expenses_api.py
moneybox/api/group_api.py
moneybox/api/incomes_api.py
moneybox/api/invites_api.py
moneybox/api/reports_api.py
moneybox/api/transfers_api.py
moneybox/api/users_api.py
moneybox/api/wallets_api.py
moneybox/models/__init__.py
moneybox/models/api_user.py
moneybox/models/currency.py
moneybox/models/currency_rate.py
moneybox/models/expense.py
moneybox/models/expense_category.py
moneybox/models/group.py
moneybox/models/income.py
moneybox/models/income_category.py
moneybox/models/invite.py
moneybox/models/paginated_api_user_list.py
moneybox/models/paginated_currency_list.py
moneybox/models/paginated_currency_rate_list.py
moneybox/models/paginated_expense_category_list.py
moneybox/models/paginated_expense_list.py
moneybox/models/paginated_group_list.py
moneybox/models/paginated_income_category_list.py
moneybox/models/paginated_income_list.py
moneybox/models/paginated_transfer_list.py
moneybox/models/paginated_wallet_list.py
moneybox/models/patched_api_user.py
moneybox/models/patched_currency.py
moneybox/models/patched_currency_rate.py
moneybox/models/patched_expense.py
moneybox/models/patched_expense_category.py
moneybox/models/patched_group.py
moneybox/models/patched_income.py
moneybox/models/patched_income_category.py
moneybox/models/patched_transfer.py
moneybox/models/patched_wallet.py
moneybox/models/report.py
moneybox/models/signup.py
moneybox/models/transfer.py
moneybox/models/wallet.py
moneybox_sdk-0.0.1rc19.dist-info/METADATA
moneybox_sdk-0.0.1rc19.dist-info/WHEEL
moneybox_sdk-0.0.1rc19.dist-info/top_level.txt
moneybox_sdk-0.0.1rc19.dist-info/RECORD
